BlizzardWarcraftAPI/BlizzardAuthToken.py
BlizzardWarcraftAPI/BlizzardWarcraftAPI.py
BlizzardWarcraftAPI/__init__.py
BlizzardWarcraftAPI/data.py
BlizzardWarcraftAPI/exceptions.py
BlizzardWarcraftAPI/modules/BlizzardWarcraftAPI_base.py
BlizzardWarcraftAPI/modules/__init__.py
BlizzardWarcraftAPI/modules/gameData/AchievementAPI.py
BlizzardWarcraftAPI/modules/gameData/AuctionHouseAPI.py
BlizzardWarcraftAPI/modules/gameData/ConnectedRealmAPI.py
BlizzardWarcraftAPI/modules/gameData/CreatureAPI.py
BlizzardWarcraftAPI/modules/gameData/GuildCrestAPI.py
BlizzardWarcraftAPI/modules/gameData/HeirloomAPI.py
BlizzardWarcraftAPI/modules/gameData/ItemAPI.py
BlizzardWarcraftAPI/modules/gameData/JournalAPI.py
BlizzardWarcraftAPI/modules/gameData/PlayableClassAPI.py
BlizzardWarcraftAPI/modules/gameData/PlayableRaceAPI.py
BlizzardWarcraftAPI/modules/gameData/PvPSeasonAPI.py
BlizzardWarcraftAPI/modules/gameData/__init__.py
BlizzardWarcraftAPI/modules/profile/AccountProfileAPI.py
BlizzardWarcraftAPI/modules/profile/CharacterAchievementsAPI.py
BlizzardWarcraftAPI/modules/profile/CharacterAppearanceAPI.py
BlizzardWarcraftAPI/modules/profile/CharacterCollectionsAPI.py
BlizzardWarcraftAPI/modules/profile/CharacterEncountersAPI.py
BlizzardWarcraftAPI/modules/profile/CharacterEquipmentAPI.py
BlizzardWarcraftAPI/modules/profile/CharacterHunterPetsAPI.py
BlizzardWarcraftAPI/modules/profile/CharacterMediaAPI.py
BlizzardWarcraftAPI/modules/profile/CharacterMythicKeystoneProfile.py
BlizzardWarcraftAPI/modules/profile/CharacterProfessionsAPI.py
BlizzardWarcraftAPI/modules/profile/CharacterProfileAPI.py
BlizzardWarcraftAPI/modules/profile/CharacterPvPAPI.py
BlizzardWarcraftAPI/modules/profile/__init__.py
BlizzardWarcraftAPI/modules/request/__init__.py
BlizzardWarcraftAPI/modules/request/href.py
BlizzardWarcraftAPI/urls.py
blizzardwarcraftapi-0.2.7.2.dist-info/LICENSE
blizzardwarcraftapi-0.2.7.2.dist-info/METADATA
blizzardwarcraftapi-0.2.7.2.dist-info/WHEEL
blizzardwarcraftapi-0.2.7.2.dist-info/RECORD
