Metadata-Version: 2.1
Name: BlizzardWarcraftAPI
Version: 0.2.7.2
Summary: Warcraft API
Home-page: https://github.com/Angeloffy/BlizzardWarcraftAPI/tree/main
License: MIT
Author: Angeloffy
Author-email: angeloffy.work@gmail.com
Maintainer: Angeloffy
Maintainer-email: angeloffy.work@gmail.com
Requires-Python: >=3.9,<4.0
Classifier: License :: OSI Approved :: MIT License
Classifier: Operating System :: OS Independent
Classifier: Programming Language :: Python :: 3
Classifier: Programming Language :: Python :: 3.9
Classifier: Programming Language :: Python :: 3.10
Classifier: Programming Language :: Python :: 3.11
Classifier: Programming Language :: Python :: 3.12
Requires-Dist: pre-commit (>=3.3.3,<4.0.0)
Requires-Dist: python-dotenv (>=1.0.0,<2.0.0)
Requires-Dist: requests (>=2.31.0,<3.0.0)
Project-URL: Bug Tracker, https://github.com/Angeloffy/BlizzardWarcraftAPI/issues
Project-URL: Repository, https://github.com/Angeloffy/BlizzardWarcraftAPI/
